openapi_client/__init__.py
openapi_client/api_client.py
openapi_client/api_response.py
openapi_client/configuration.py
openapi_client/exceptions.py
openapi_client/py.typed
openapi_client/rest.py
openapi_client/api/__init__.py
openapi_client/api/default_api.py
openapi_client/models/__init__.py
openapi_client/models/account_response.py
openapi_client/models/action_row_component_for_message_request.py
openapi_client/models/action_row_component_for_message_request_components_inner.py
openapi_client/models/action_row_component_for_modal_request.py
openapi_client/models/action_row_component_response.py
openapi_client/models/action_row_component_response_components_inner.py
openapi_client/models/activities_attachment_response.py
openapi_client/models/add_group_dm_user201_response.py
openapi_client/models/add_group_dm_user_request.py
openapi_client/models/add_lobby_member_request.py
openapi_client/models/application_command_attachment_option.py
openapi_client/models/application_command_attachment_option_response.py
openapi_client/models/application_command_autocomplete_callback_request.py
openapi_client/models/application_command_autocomplete_callback_request_data.py
openapi_client/models/application_command_boolean_option.py
openapi_client/models/application_command_boolean_option_response.py
openapi_client/models/application_command_channel_option.py
openapi_client/models/application_command_channel_option_response.py
openapi_client/models/application_command_create_request.py
openapi_client/models/application_command_create_request_options_inner.py
openapi_client/models/application_command_integer_option.py
openapi_client/models/application_command_integer_option_response.py
openapi_client/models/application_command_interaction_metadata_response.py
openapi_client/models/application_command_mentionable_option.py
openapi_client/models/application_command_mentionable_option_response.py
openapi_client/models/application_command_number_option.py
discordopenapi-1.0.0.dist-info/METADATA
discordopenapi-1.0.0.dist-info/WHEEL
discordopenapi-1.0.0.dist-info/top_level.txt
discordopenapi-1.0.0.dist-info/RECORD
